llmrails/client.py
llmrails/exceptions.py
llmrails/models.py
llmrails/utils.py
llmrails-0.1.4.dist-info/LICENSE
llmrails-0.1.4.dist-info/METADATA
llmrails-0.1.4.dist-info/WHEEL
llmrails-0.1.4.dist-info/RECORD
