Metadata-Version: 2.1
Name: llmrails
Version: 0.1.4
Summary: LLMRails SDK
License: MIT
Author: LLMRails
Requires-Python: >=3.7,<4.0
Classifier: License :: OSI Approved :: MIT License
Classifier: Programming Language :: Python :: 3
Classifier: Programming Language :: Python :: 3.7
Classifier: Programming Language :: Python :: 3.8
Classifier: Programming Language :: Python :: 3.9
Classifier: Programming Language :: Python :: 3.10
Classifier: Programming Language :: Python :: 3.11
Requires-Dist: dacite (==1.8.1)
Requires-Dist: requests (==2.31.0)
